examples/__init__.py
examples/mongo/__init__.py
examples/mongo/__main__.py
examples/mongo/service.py
examples/mongo/settings.ini
examples/ping_pong/__init__.py
examples/ping_pong/__main__.py
examples/ping_pong/module.py
examples/ping_pong/service.py
examples/ping_pong/settings.ini
tests/__init__.py
tests/test_app.py
tests/test_controller.py
tests/test_module.py
tests/test_service.py
tests/test_settings.ini
tests/test_zmq_controller.py
wolverine/__init__.py
wolverine/settings.ini
wolverine/db/__init__.py
wolverine/db/mongo.ini
wolverine/db/mongo.py
wolverine/discovery/__init__.py
wolverine/discovery/consul.ini
wolverine/discovery/consul.py
wolverine/gateway/__init__.py
wolverine/gateway/settings.ini
wolverine/module/__init__.py
wolverine/module/controller/__init__.py
wolverine/module/controller/zhelpers.py
wolverine/module/controller/zmq.py
wolverine/module/service/__init__.py
wolverine/module/service/zhelpers.py
wolverine/module/service/zmq.py
wolverine/modules/__init__.py
wolverine/modules/zhelpers.py
wolverine/modules/zmq.py
wolverine/routers/__init__.py
wolverine/shell/__init__.py
wolverine/shell/__main__.py
wolverine/shell/settings.ini
wolverine/test/__init__.py
wolverine/web/__init__.py
wolverine/web/__main__.py
wolverine/web/settings.ini
wolverine-0.3.4.dist-info/DESCRIPTION.rst
wolverine-0.3.4.dist-info/METADATA
wolverine-0.3.4.dist-info/RECORD
wolverine-0.3.4.dist-info/WHEEL
wolverine-0.3.4.dist-info/metadata.json
wolverine-0.3.4.dist-info/top_level.txt
