Metadata-Version: 2.0
Name: wolverine
Version: 0.3.4
Summary: micro service framework with python 3.5 and asyncio
Home-page: http://github.com/drankinn/wolverine
Author: Lance Andersen
Author-email: techlance@gmail.com
License: MIT 2.0
Platform: UNKNOWN
Requires-Dist: aiohttp (>=0.19.0)
Requires-Dist: aiozmq (>=0.7.1)
Requires-Dist: msgpack-python (>=0.4.6)
Requires-Dist: python-consul (>=0.4.7)
Requires-Dist: pyzmq (>=15.1.0)
